edgectl/__init__.py
edgectl/__main__.py
edgectl/auth.py
edgectl/camera.py
edgectl/device.py
edgectl/main.py
edgectl/scenario.py
edgectl-0.1.2.dist-info/entry_points.txt
edgectl-0.1.2.dist-info/WHEEL
edgectl-0.1.2.dist-info/METADATA
edgectl-0.1.2.dist-info/RECORD
