Metadata-Version: 2.1
Name: edgectl
Version: 0.1.2
Summary: 
Author: Harsh Murari
Author-email: hmurari@visionify.ai
Requires-Python: >=3.7,<4.0
Classifier: Programming Language :: Python :: 3
Classifier: Programming Language :: Python :: 3.7
Classifier: Programming Language :: Python :: 3.8
Classifier: Programming Language :: Python :: 3.9
Classifier: Programming Language :: Python :: 3.10
Classifier: Programming Language :: Python :: 3.11
Requires-Dist: requests (>=2.28.2,<3.0.0)
Requires-Dist: typer[all] (>=0.7.0,<0.8.0)
